unitypack/__init__.py
unitypack/asset.py
unitypack/assetbundle.py
unitypack/classes.json
unitypack/enums.py
unitypack/environment.py
unitypack/export.py
unitypack/object.py
unitypack/resources.py
unitypack/strings.dat
unitypack/structs.dat
unitypack/type.py
unitypack/utils.py
unitypack/engine/__init__.py
unitypack/engine/animation.py
unitypack/engine/audio.py
unitypack/engine/component.py
unitypack/engine/font.py
unitypack/engine/mesh.py
unitypack/engine/movie.py
unitypack/engine/object.py
unitypack/engine/particle.py
unitypack/engine/physics.py
unitypack/engine/renderer.py
unitypack/engine/text.py
unitypack/engine/texture.py
unitypack-0.9.0.data/scripts/unity2yaml
unitypack-0.9.0.data/scripts/unityextract
unitypack-0.9.0.dist-info/DESCRIPTION.rst
unitypack-0.9.0.dist-info/METADATA
unitypack-0.9.0.dist-info/RECORD
unitypack-0.9.0.dist-info/WHEEL
unitypack-0.9.0.dist-info/metadata.json
unitypack-0.9.0.dist-info/top_level.txt
