Metadata-Version: 2.0
Name: unitypack
Version: 0.9.0
Summary: Python implementation of the .unity3d format
Home-page: https://github.com/HearthSim/UnityPack
Author: Jerome Leclanche
Author-email: jerome@leclan.ch
License: UNKNOWN
Download-URL: https://github.com/HearthSim/UnityPack/tarball/master
Platform: UNKNOWN
Classifier: Development Status :: 4 - Beta
Classifier: Intended Audience :: Developers
Classifier: License :: OSI Approved :: MIT License
Classifier: Programming Language :: Python
Classifier: Programming Language :: Python :: 3
Classifier: Programming Language :: Python :: 3.6
Classifier: Topic :: Multimedia :: Graphics
Requires-Dist: decrunch
Requires-Dist: fsb5
Requires-Dist: lz4
Requires-Dist: Pillow
